adapt/__init__.py
adapt/calcmags.py
adapt_fw-0.0.1.dist-info/LICENSE.txt
adapt_fw-0.0.1.dist-info/METADATA
adapt_fw-0.0.1.dist-info/WHEEL
adapt_fw-0.0.1.dist-info/top_level.txt
adapt_fw-0.0.1.dist-info/RECORD
