Metadata-Version: 2.1
Name: adapt-fw
Version: 0.0.1
Summary: ADAptive Picking Toolbox: a framework for seismic picking
Home-page: https://gitlab.ethz.ch/mbagagli
Author: Matteo Bagagli
Author-email: matteo.bagagli@erdw.ethz.com
License: UNKNOWN
Platform: UNKNOWN
Classifier: Programming Language :: Python :: 3
Classifier: Programming Language :: Python :: 3.6
Classifier: Programming Language :: Python :: 3.7
Classifier: License :: OSI Approved :: GNU General Public License v3 (GPLv3)
Classifier: Operating System :: Unix
Classifier: Operating System :: MacOS
Classifier: Topic :: Software Development :: Libraries
Classifier: Intended Audience :: Science/Research
Classifier: Intended Audience :: Developers
Requires-Python: >=3.6
Requires-Dist: numpy (>=1.18.1)
Requires-Dist: obspy (>=1.1.0)
Requires-Dist: pytest (>=3.7)
